[
    {
        "id": "imbemr.imbFormsApp",
        "description": "IMB Forms App",
        "extensionPoints": [
            {
                "id": "imbForms.apps",
                "description": "IMB Forms"
            }
        ],
        "extensions": [
            {
                "id": "imbemr.imbforms.homepageLink",
                "extensionPointId": "org.openmrs.referenceapplication.homepageLink",
                "type": "link",
                "label": "IMB Forms",
                "url": "imbemr/imbforms/imbForms.page",
                "icon": "icon-file",
                "order": 100,
                "requiredPrivilege": "App: imbemr.imbForms"
            }
        ]
    }
]